myrepos_utils/__init__.py
myrepos_utils/__main__.py
myrepos_utils/cli.py
myrepos_utils/utils.py
myrepos_utils/tests/__init__.py
myrepos_utils/tests/test_utils.py
myrepos_utils-0.0.4.2.dist-info/COPYING.md
myrepos_utils-0.0.4.2.dist-info/METADATA
myrepos_utils-0.0.4.2.dist-info/WHEEL
myrepos_utils-0.0.4.2.dist-info/entry_points.txt
myrepos_utils-0.0.4.2.dist-info/top_level.txt
myrepos_utils-0.0.4.2.dist-info/RECORD
