Metadata-Version: 2.1
Name: myrepos-utils
Version: 0.0.4.2
Summary: Additional utilities for myrepos
Home-page: https://git.sr.ht/~michel-slm/myrepos-utils
Author: Michel Lind
Author-email: michel@michel-slm.name
Classifier: Development Status :: 3 - Alpha
Classifier: Environment :: Console
Classifier: License :: OSI Approved :: GNU General Public License v2 or later (GPLv2+)
License-File: COPYING.md
Requires-Dist: click
Provides-Extra: dev
Requires-Dist: black ; extra == 'dev'
Requires-Dist: build ; extra == 'dev'
Requires-Dist: pip-tools ; extra == 'dev'
Requires-Dist: pytest ; extra == 'dev'
Requires-Dist: pytest-cov ; extra == 'dev'
Provides-Extra: release
Requires-Dist: twine ; extra == 'release'
Provides-Extra: test
Requires-Dist: pytest ; extra == 'test'
